{
  "version": "1.0",
  "lastUpdated": "2025-12-18T11:40:52.367Z",
  "reports": [
    {
      "id": "report-1766042552185",
      "title": "車載全球客戶實績簡介",
      "description": "Automotive Global Customer Achievements",
      "categories": [
        "客戶簡報",
        "內部簡報",
        "其他"
      ],
      "fileName": "report-1766042552185.html",
      "createdAt": "2025-12-18T07:22:32.941Z",
      "updatedAt": "2025-12-18T07:22:32.941Z"
    },
    {
      "id": "report-1766046190926",
      "title": "2025年 全球客戶實績總覽",
      "description": "2025 Global Customer Achievements",
      "categories": [
        "客戶簡報",
        "內部簡報",
        "其他"
      ],
      "fileName": "report-1766046190926.html",
      "createdAt": "2025-12-18T08:23:11.373Z",
      "updatedAt": "2025-12-18T08:23:11.373Z"
    },
    {
      "id": "report-1766046354891",
      "title": "Foxlink簡介和實績",
      "description": "Foxlink Profile and Achievements",
      "categories": [
        "客戶簡報",
        "內部簡報",
        "其他"
      ],
      "fileName": "report-1766046354891.html",
      "createdAt": "2025-12-18T08:25:55.301Z",
      "updatedAt": "2025-12-18T08:25:55.301Z"
    },
    {
      "id": "report-1766046848878",
      "title": "印度WhatsApp話術攻略生成器",
      "description": "印度WhatsApp話術攻略生成器",
      "categories": [
        "客戶簡報",
        "內部簡報",
        "其他"
      ],
      "fileName": "report-1766046848878.html",
      "createdAt": "2025-12-18T08:34:09.636Z",
      "updatedAt": "2025-12-18T08:34:09.636Z"
    },
    {
      "id": "report-1766047005427",
      "title": "全方位戰略評估：Syrma SGS Technology (Jasbir Singh Gujral)",
      "description": "Strategic Analysis: Syrma SGS Technology (Jasbir Singh Gujral)",
      "categories": [
        "內部簡報",
        "市場分析",
        "項目計劃"
      ],
      "fileName": "report-1766047005427.html",
      "createdAt": "2025-12-18T08:36:45.874Z",
      "updatedAt": "2025-12-18T08:36:45.874Z"
    },
    {
      "id": "report-1766053995273",
      "title": "集團子公司與全球製造據點完整清單",
      "description": "Global Subsidiaries & Manufacturing Sites",
      "categories": [
        "客戶簡報",
        "內部簡報",
        "市場分析"
      ],
      "fileName": "report-1766053995273.html",
      "createdAt": "2025-12-18T10:33:16.490Z",
      "updatedAt": "2025-12-18T10:33:16.490Z"
    },
    {
      "id": "report-1766055749918",
      "title": "Strategic Matchmaking Profile & Capabilities",
      "description": "Strategic Matchmaking Profile & Capabilities",
      "categories": [
        "客戶簡報",
        "內部簡報",
        "項目計劃"
      ],
      "fileName": "report-1766055749918.html",
      "createdAt": "2025-12-18T11:02:31.583Z",
      "updatedAt": "2025-12-18T11:40:52.367Z"
    }
  ]
}